setup.cfg
setup.py
hnctools/__init__.py
hnctools/i18n.py
hnctools/oauth.py
hnctools/renderers.py
hnctools/request.py
hnctools/routing.py
hnctools/smtplogging.py
hnctools/tools.py
hnctools/urlnormalize.py
hnctools.egg-info/PKG-INFO
hnctools.egg-info/SOURCES.txt
hnctools.egg-info/dependency_links.txt
hnctools.egg-info/entry_points.txt
hnctools.egg-info/requires.txt
hnctools.egg-info/top_level.txt
hnctools.egg-info/zip-safe