Metadata-Version: 1.0
Name: hnctools
Version: 0.1.6dev
Summary: HnC tools for pyramid
Home-page: http://www.hackandcraft.com
Author: Martin Peschke
Author-email: martin@hackandcraft.com
License: UNKNOWN
Platform: UNKNOWN
